LICENSE
MANIFEST.in
README.md
README.rst
requirements.txt
setup.cfg
setup.py
versioneer.py
flask_basic_roles/__init__.py
flask_basic_roles/_version.py
flask_basic_roles.egg-info/PKG-INFO
flask_basic_roles.egg-info/SOURCES.txt
flask_basic_roles.egg-info/dependency_links.txt
flask_basic_roles.egg-info/requires.txt
flask_basic_roles.egg-info/top_level.txt