Metadata-Version: 1.1
Name: flask-basic-roles
Version: 0.2
Summary: A plugin for adding very simple users + roles to a flask app
Home-page: https://github.com/ownaginatious/flask-basic-roles
Author: Dillon Dixon
Author-email: dillondixon@gmail.com
License: MIT
Keywords: flask,python,authentication,authorization
Platform: UNKNOWN
Classifier: Framework :: Flask
Classifier: License :: OSI Approved :: MIT License
Classifier: Programming Language :: Python :: 2.7
Classifier: Programming Language :: Python :: 3.3
Classifier: Programming Language :: Python :: 3.4
Classifier: Programming Language :: Python :: 3.5
